trustme/__init__.py
trustme/__main__.py
trustme/_cli.py
trustme/_version.py
trustme/py.typed
trustme-1.1.0.dist-info/LICENSE
trustme-1.1.0.dist-info/LICENSE.APACHE2
trustme-1.1.0.dist-info/LICENSE.MIT
trustme-1.1.0.dist-info/METADATA
trustme-1.1.0.dist-info/WHEEL
trustme-1.1.0.dist-info/top_level.txt
trustme-1.1.0.dist-info/RECORD
